jsl/__init__.py
jsl/cli.py
jsl/compiler.py
jsl/core.py
jsl/eval_modes.py
jsl/fluent.py
jsl/prelude.py
jsl/resources.py
jsl/runner.py
jsl/serialization.py
jsl/sexp.py
jsl/stack_evaluator.py
jsl/stack_special_forms.py
jsl_lang-0.4.0.dist-info/licenses/LICENSE
jsl_lang-0.4.0.dist-info/METADATA
jsl_lang-0.4.0.dist-info/WHEEL
jsl_lang-0.4.0.dist-info/entry_points.txt
jsl_lang-0.4.0.dist-info/top_level.txt
jsl_lang-0.4.0.dist-info/RECORD
